{
  "breakpoints": {
    "375": {
      "name": "shared-card-grid",
      "viewportWidth": 323,
      "width": 323,
      "height": 2586,
      "bones": [
        [
          0,
          0,
          100,
          417,
          19.6875,
          true
        ],
        [
          0.3101,
          1,
          99.3798,
          240,
          8
        ],
        [
          5.3973,
          258,
          24.4186,
          20,
          9.84375
        ],
        [
          78.3236,
          258,
          16.2791,
          20,
          9.84375
        ],
        [
          5.3973,
          287,
          71.3614,
          20,
          9.84375
        ],
        [
          5.3973,
          317,
          89.2054,
          10,
          9.84375
        ],
        [
          5.3973,
          333,
          59.4671,
          10,
          9.84375
        ],
        [
          5.3973,
          374,
          8.1395,
          26,
          9.84375
        ],
        [
          15.5717,
          382,
          24.4186,
          10,
          9.84375
        ],
        [
          74.2539,
          374,
          20.3488,
          26,
          9.84375
        ],
        [
          0,
          434,
          100,
          417,
          19.6875,
          true
        ],
        [
          0.3101,
          435,
          99.3798,
          240,
          8
        ],
        [
          5.3973,
          691,
          24.4186,
          20,
          9.84375
        ],
        [
          78.3236,
          691,
          16.2791,
          20,
          9.84375
        ],
        [
          5.3973,
          721,
          71.3614,
          20,
          9.84375
        ],
        [
          5.3973,
          751,
          89.2054,
          10,
          9.84375
        ],
        [
          5.3973,
          767,
          59.4671,
          10,
          9.84375
        ],
        [
          5.3973,
          807,
          8.1395,
          26,
          9.84375
        ],
        [
          15.5717,
          816,
          24.4186,
          10,
          9.84375
        ],
        [
          74.2539,
          807,
          20.3488,
          26,
          9.84375
        ],
        [
          0,
          867,
          100,
          417,
          19.6875,
          true
        ],
        [
          0.3101,
          868,
          99.3798,
          240,
          8
        ],
        [
          5.3973,
          1125,
          24.4186,
          20,
          9.84375
        ],
        [
          78.3236,
          1125,
          16.2791,
          20,
          9.84375
        ],
        [
          5.3973,
          1155,
          71.3614,
          20,
          9.84375
        ],
        [
          5.3973,
          1184,
          89.2054,
          10,
          9.84375
        ],
        [
          5.3973,
          1201,
          59.4671,
          10,
          9.84375
        ],
        [
          5.3973,
          1241,
          8.1395,
          26,
          9.84375
        ],
        [
          15.5717,
          1249,
          24.4186,
          10,
          9.84375
        ],
        [
          74.2539,
          1241,
          20.3488,
          26,
          9.84375
        ],
        [
          0,
          1301,
          100,
          417,
          19.6875,
          true
        ],
        [
          0.3101,
          1302,
          99.3798,
          240,
          8
        ],
        [
          5.3973,
          1559,
          24.4186,
          20,
          9.84375
        ],
        [
          78.3236,
          1559,
          16.2791,
          20,
          9.84375
        ],
        [
          5.3973,
          1588,
          71.3614,
          20,
          9.84375
        ],
        [
          5.3973,
          1618,
          89.2054,
          10,
          9.84375
        ],
        [
          5.3973,
          1634,
          59.4671,
          10,
          9.84375
        ],
        [
          5.3973,
          1675,
          8.1395,
          26,
          9.84375
        ],
        [
          15.5717,
          1683,
          24.4186,
          10,
          9.84375
        ],
        [
          74.2539,
          1675,
          20.3488,
          26,
          9.84375
        ],
        [
          0,
          1735,
          100,
          417,
          19.6875,
          true
        ],
        [
          0.3101,
          1736,
          99.3798,
          240,
          8
        ],
        [
          5.3973,
          1993,
          24.4186,
          20,
          9.84375
        ],
        [
          78.3236,
          1993,
          16.2791,
          20,
          9.84375
        ],
        [
          5.3973,
          2022,
          71.3614,
          20,
          9.84375
        ],
        [
          5.3973,
          2052,
          89.2054,
          10,
          9.84375
        ],
        [
          5.3973,
          2068,
          59.4671,
          10,
          9.84375
        ],
        [
          5.3973,
          2108,
          8.1395,
          26,
          9.84375
        ],
        [
          15.5717,
          2117,
          24.4186,
          10,
          9.84375
        ],
        [
          74.2539,
          2108,
          20.3488,
          26,
          9.84375
        ],
        [
          0,
          2168,
          100,
          417,
          19.6875,
          true
        ],
        [
          0.3101,
          2169,
          99.3798,
          240,
          8
        ],
        [
          5.3973,
          2426,
          24.4186,
          20,
          9.84375
        ],
        [
          78.3236,
          2426,
          16.2791,
          20,
          9.84375
        ],
        [
          5.3973,
          2456,
          71.3614,
          20,
          9.84375
        ],
        [
          5.3973,
          2485,
          89.2054,
          10,
          9.84375
        ],
        [
          5.3973,
          2502,
          59.4671,
          10,
          9.84375
        ],
        [
          5.3973,
          2542,
          8.1395,
          26,
          9.84375
        ],
        [
          15.5717,
          2550,
          24.4186,
          10,
          9.84375
        ],
        [
          74.2539,
          2542,
          20.3488,
          26,
          9.84375
        ]
      ]
    },
    "768": {
      "name": "shared-card-grid",
      "viewportWidth": 704,
      "width": 704,
      "height": 1450,
      "bones": [
        [
          0,
          0,
          48.5795,
          470,
          24,
          true
        ],
        [
          0.142,
          1,
          48.2955,
          255,
          8
        ],
        [
          2.983,
          276,
          13.6364,
          24,
          12
        ],
        [
          36.5057,
          276,
          9.0909,
          24,
          12
        ],
        [
          2.983,
          312,
          34.0909,
          24,
          12
        ],
        [
          2.983,
          348,
          42.6136,
          12,
          12
        ],
        [
          2.983,
          368,
          28.4091,
          12,
          12
        ],
        [
          2.983,
          417,
          4.5455,
          32,
          12
        ],
        [
          8.6648,
          427,
          13.6364,
          12,
          12
        ],
        [
          34.233,
          417,
          11.3636,
          32,
          12
        ],
        [
          51.4205,
          0,
          48.5795,
          470,
          24,
          true
        ],
        [
          51.5625,
          1,
          48.2955,
          255,
          8
        ],
        [
          54.4034,
          276,
          13.6364,
          24,
          12
        ],
        [
          87.9261,
          276,
          9.0909,
          24,
          12
        ],
        [
          54.4034,
          312,
          34.0909,
          24,
          12
        ],
        [
          54.4034,
          348,
          42.6136,
          12,
          12
        ],
        [
          54.4034,
          368,
          28.4091,
          12,
          12
        ],
        [
          54.4034,
          417,
          4.5455,
          32,
          12
        ],
        [
          60.0852,
          427,
          13.6364,
          12,
          12
        ],
        [
          85.6534,
          417,
          11.3636,
          32,
          12
        ],
        [
          0,
          490,
          48.5795,
          470,
          24,
          true
        ],
        [
          0.142,
          491,
          48.2955,
          255,
          8
        ],
        [
          2.983,
          766,
          13.6364,
          24,
          12
        ],
        [
          36.5057,
          766,
          9.0909,
          24,
          12
        ],
        [
          2.983,
          802,
          34.0909,
          24,
          12
        ],
        [
          2.983,
          838,
          42.6136,
          12,
          12
        ],
        [
          2.983,
          858,
          28.4091,
          12,
          12
        ],
        [
          2.983,
          907,
          4.5455,
          32,
          12
        ],
        [
          8.6648,
          917,
          13.6364,
          12,
          12
        ],
        [
          34.233,
          907,
          11.3636,
          32,
          12
        ],
        [
          51.4205,
          490,
          48.5795,
          470,
          24,
          true
        ],
        [
          51.5625,
          491,
          48.2955,
          255,
          8
        ],
        [
          54.4034,
          766,
          13.6364,
          24,
          12
        ],
        [
          87.9261,
          766,
          9.0909,
          24,
          12
        ],
        [
          54.4034,
          802,
          34.0909,
          24,
          12
        ],
        [
          54.4034,
          838,
          42.6136,
          12,
          12
        ],
        [
          54.4034,
          858,
          28.4091,
          12,
          12
        ],
        [
          54.4034,
          907,
          4.5455,
          32,
          12
        ],
        [
          60.0852,
          917,
          13.6364,
          12,
          12
        ],
        [
          85.6534,
          907,
          11.3636,
          32,
          12
        ],
        [
          0,
          980,
          48.5795,
          470,
          24,
          true
        ],
        [
          0.142,
          981,
          48.2955,
          255,
          8
        ],
        [
          2.983,
          1256,
          13.6364,
          24,
          12
        ],
        [
          36.5057,
          1256,
          9.0909,
          24,
          12
        ],
        [
          2.983,
          1292,
          34.0909,
          24,
          12
        ],
        [
          2.983,
          1328,
          42.6136,
          12,
          12
        ],
        [
          2.983,
          1348,
          28.4091,
          12,
          12
        ],
        [
          2.983,
          1397,
          4.5455,
          32,
          12
        ],
        [
          8.6648,
          1407,
          13.6364,
          12,
          12
        ],
        [
          34.233,
          1397,
          11.3636,
          32,
          12
        ],
        [
          51.4205,
          980,
          48.5795,
          470,
          24,
          true
        ],
        [
          51.5625,
          981,
          48.2955,
          255,
          8
        ],
        [
          54.4034,
          1256,
          13.6364,
          24,
          12
        ],
        [
          87.9261,
          1256,
          9.0909,
          24,
          12
        ],
        [
          54.4034,
          1292,
          34.0909,
          24,
          12
        ],
        [
          54.4034,
          1328,
          42.6136,
          12,
          12
        ],
        [
          54.4034,
          1348,
          28.4091,
          12,
          12
        ],
        [
          54.4034,
          1397,
          4.5455,
          32,
          12
        ],
        [
          60.0852,
          1407,
          13.6364,
          12,
          12
        ],
        [
          85.6534,
          1397,
          11.3636,
          32,
          12
        ]
      ]
    },
    "1280": {
      "name": "shared-card-grid",
      "viewportWidth": 1216,
      "width": 1216,
      "height": 1035,
      "bones": [
        [
          0,
          0,
          32.2368,
          508,
          24,
          true
        ],
        [
          0.0822,
          1,
          32.0724,
          293,
          8
        ],
        [
          1.727,
          314,
          7.8947,
          24,
          12
        ],
        [
          25.2467,
          314,
          5.2632,
          24,
          12
        ],
        [
          1.727,
          350,
          23.0263,
          24,
          12
        ],
        [
          1.727,
          386,
          28.7829,
          12,
          12
        ],
        [
          1.727,
          406,
          19.1882,
          12,
          12
        ],
        [
          1.727,
          455,
          2.6316,
          32,
          12
        ],
        [
          5.0164,
          465,
          7.8947,
          12,
          12
        ],
        [
          23.9309,
          455,
          6.5789,
          32,
          12
        ],
        [
          33.8816,
          0,
          32.2368,
          508,
          24,
          true
        ],
        [
          33.9638,
          1,
          32.0724,
          293,
          8
        ],
        [
          35.6086,
          314,
          7.8947,
          24,
          12
        ],
        [
          59.1283,
          314,
          5.2632,
          24,
          12
        ],
        [
          35.6086,
          350,
          23.0263,
          24,
          12
        ],
        [
          35.6086,
          386,
          28.7829,
          12,
          12
        ],
        [
          35.6086,
          406,
          19.1882,
          12,
          12
        ],
        [
          35.6086,
          455,
          2.6316,
          32,
          12
        ],
        [
          38.898,
          465,
          7.8947,
          12,
          12
        ],
        [
          57.8125,
          455,
          6.5789,
          32,
          12
        ],
        [
          67.7632,
          0,
          32.2368,
          508,
          24,
          true
        ],
        [
          67.8454,
          1,
          32.0724,
          293,
          8
        ],
        [
          69.4901,
          314,
          7.8947,
          24,
          12
        ],
        [
          93.0099,
          314,
          5.2632,
          24,
          12
        ],
        [
          69.4901,
          350,
          23.0263,
          24,
          12
        ],
        [
          69.4901,
          386,
          28.7829,
          12,
          12
        ],
        [
          69.4901,
          406,
          19.1882,
          12,
          12
        ],
        [
          69.4901,
          455,
          2.6316,
          32,
          12
        ],
        [
          72.7796,
          465,
          7.8947,
          12,
          12
        ],
        [
          91.6941,
          455,
          6.5789,
          32,
          12
        ],
        [
          0,
          528,
          32.2368,
          508,
          24,
          true
        ],
        [
          0.0822,
          529,
          32.0724,
          293,
          8
        ],
        [
          1.727,
          841,
          7.8947,
          24,
          12
        ],
        [
          25.2467,
          841,
          5.2632,
          24,
          12
        ],
        [
          1.727,
          877,
          23.0263,
          24,
          12
        ],
        [
          1.727,
          913,
          28.7829,
          12,
          12
        ],
        [
          1.727,
          933,
          19.1882,
          12,
          12
        ],
        [
          1.727,
          982,
          2.6316,
          32,
          12
        ],
        [
          5.0164,
          992,
          7.8947,
          12,
          12
        ],
        [
          23.9309,
          982,
          6.5789,
          32,
          12
        ],
        [
          33.8816,
          528,
          32.2368,
          508,
          24,
          true
        ],
        [
          33.9638,
          529,
          32.0724,
          293,
          8
        ],
        [
          35.6086,
          841,
          7.8947,
          24,
          12
        ],
        [
          59.1283,
          841,
          5.2632,
          24,
          12
        ],
        [
          35.6086,
          877,
          23.0263,
          24,
          12
        ],
        [
          35.6086,
          913,
          28.7829,
          12,
          12
        ],
        [
          35.6086,
          933,
          19.1882,
          12,
          12
        ],
        [
          35.6086,
          982,
          2.6316,
          32,
          12
        ],
        [
          38.898,
          992,
          7.8947,
          12,
          12
        ],
        [
          57.8125,
          982,
          6.5789,
          32,
          12
        ],
        [
          67.7632,
          528,
          32.2368,
          508,
          24,
          true
        ],
        [
          67.8454,
          529,
          32.0724,
          293,
          8
        ],
        [
          69.4901,
          841,
          7.8947,
          24,
          12
        ],
        [
          93.0099,
          841,
          5.2632,
          24,
          12
        ],
        [
          69.4901,
          877,
          23.0263,
          24,
          12
        ],
        [
          69.4901,
          913,
          28.7829,
          12,
          12
        ],
        [
          69.4901,
          933,
          19.1882,
          12,
          12
        ],
        [
          69.4901,
          982,
          2.6316,
          32,
          12
        ],
        [
          72.7796,
          992,
          7.8947,
          12,
          12
        ],
        [
          91.6941,
          982,
          6.5789,
          32,
          12
        ]
      ]
    }
  },
  "_hash": "0a5d1239c0ee4bbc79fc4a446efef459"
}